GUIPyDebugger/__init__.py
GUIPyDebugger/asgi.py
GUIPyDebugger/settings.py
GUIPyDebugger/urls.py
GUIPyDebugger/wsgi.py
about/__init__.py
about/admin.py
about/apps.py
about/models.py
about/tests.py
about/urls.py
about/views.py
about/migrations/__init__.py
core/__init__.py
core/collector.py
core/manage.py
core/output.txt
core/start.py
diagrammer/__init__.py
diagrammer/admin.py
diagrammer/apps.py
diagrammer/models.py
diagrammer/module_info.py
diagrammer/tests.py
diagrammer/urls.py
diagrammer/utils.py
diagrammer/views.py
diagrammer/migrations/__init__.py
editor/__init__.py
editor/admin.py
editor/apps.py
editor/models.py
editor/output.txt
editor/tests.py
editor/urls.py
editor/utils.py
editor/views.py
editor/migrations/__init__.py
static/__init__.py
static/code_files/__init__.py
static/code_files/another_one.py
static/code_files/csp.py
static/code_files/driver.py
static/code_files/dummy_module.py
static/code_files/map_coloring.py
static/code_files/queens.py
static/code_files/send_more_money.py
static/code_files/word_search.py
static/code_files/test/__init__.py
static/code_files/test/cool_code.py
static/images/__init__.py
static/images/attribute.png
static/images/class.png
static/images/function.png
static/images/module.png
static/images/view.jpg
templates/__init__.py
templates/about/__init__.py
templates/about/about.html
templates/base/__init__.py
templates/base/base.html
templates/diagrammer/__init__.py
templates/diagrammer/diagram.html
templates/diagrammer/file-not-found.html
templates/diagrammer/import-error.html
templates/diagrammer/no-entry-point.html
templates/diagrammer/syntax-error.html
templates/editor/__init__.py
templates/editor/editor.html
templates/editor/no-entry-point.html
GUIPyDebugger-1.0.8.dist-info/LICENSE.txt
GUIPyDebugger-1.0.8.dist-info/METADATA
GUIPyDebugger-1.0.8.dist-info/WHEEL
GUIPyDebugger-1.0.8.dist-info/entry_points.txt
GUIPyDebugger-1.0.8.dist-info/top_level.txt
GUIPyDebugger-1.0.8.dist-info/RECORD
