Metadata-Version: 2.1
Name: GUIPyDebugger
Version: 1.0.8
Summary: GUI debugging server accessible on LAN connected devices through a browser
Home-page: https://github.com/33QWERTY33/GUI-python-debugger
Author: Curtis Jones
Author-email: curlejo.4career@gmail.com
Classifier: Programming Language :: Python :: 3
Classifier: License :: OSI Approved :: MIT License
Classifier: Operating System :: OS Independent
Requires-Python: >=3.11
License-File: LICENSE.txt
Requires-Dist: django
